Metadata-Version: 2.4
Name: django-shinobi
Version: 1.4.0
Summary: Django Shinobi - Fast Django REST framework
Home-page: https://pmdevita.github.io/django-shinobi
Author: Peter DeVita
Author-email: pmdevita2643@gmail.com
Requires-Python: >=3.8
Classifier: Intended Audience :: Information Technology
Classifier: Intended Audience :: System Administrators
Classifier: Operating System :: OS Independent
Classifier: Development Status :: 5 - Production/Stable
Classifier: Topic :: Internet
Classifier: Topic :: Software Development :: Libraries :: Application Frameworks
Classifier: Topic :: Software Development :: Libraries :: Python Modules
Classifier: Topic :: Software Development :: Libraries
Classifier: Topic :: Software Development
Classifier: Typing :: Typed
Classifier: Environment :: Web Environment
Classifier: Intended Audience :: Developers
Classifier: License :: OSI Approved :: MIT License
Classifier: Programming Language :: Python :: 3
Classifier: Programming Language :: Python :: 3.8
Classifier: Programming Language :: Python :: 3.9
Classifier: Programming Language :: Python :: 3.10
Classifier: Programming Language :: Python :: 3.11
Classifier: Programming Language :: Python :: 3.12
Classifier: Programming Language :: Python :: 3.13
Classifier: Programming Language :: Python :: 3 :: Only
Classifier: Framework :: Django
Classifier: Framework :: Django :: 4.2
Classifier: Framework :: Django :: 5.1
Classifier: Framework :: Django :: 5.2
Classifier: Framework :: AsyncIO
Classifier: Topic :: Internet :: WWW/HTTP :: HTTP Servers
Classifier: Topic :: Internet :: WWW/HTTP
License-File: LICENSE
Requires-Dist: Django >=4.2
Requires-Dist: pydantic >=2.5,<2.12
Requires-Dist: pre-commit ; extra == "dev"
Requires-Dist: mkdocs ; extra == "doc"
Requires-Dist: mkdocs-material ; extra == "doc"
Requires-Dist: markdown-include ; extra == "doc"
Requires-Dist: mkdocstrings ; extra == "doc"
Requires-Dist: pytest ; extra == "test"
Requires-Dist: pytest-cov ; extra == "test"
Requires-Dist: pytest-django ; extra == "test"
Requires-Dist: pytest-asyncio ; extra == "test"
Requires-Dist: psycopg2-binary ; extra == "test"
Requires-Dist: mypy==1.7.1 ; extra == "test"
Requires-Dist: ruff==0.5.7 ; extra == "test"
Requires-Dist: django-stubs ; extra == "test"
Project-URL: Documentation, https://pmdevita.github.io/django-shinobi
Project-URL: Repository, https://github.com/pmdevita/django-shinobi
Provides-Extra: dev
Provides-Extra: doc
Provides-Extra: test
